{"/*":["X-Frame-Options: DENY","X-XSS-Protection: 1; mode=block","X-Content-Type-Options: nosniff","Referrer-Policy: same-origin"],"/styles.d914d2ce2a548b5b61a4.css":["Cache-Control: public, max-age=31536000, immutable"],"/commons-c89ee2ae9b5486d8d1b5.js":["Cache-Control: public, max-age=31536000, immutable"],"/component---src-pages-404-js-fbb7f054aa0b704a0b9a.js":["Cache-Control: public, max-age=31536000, immutable"],"/component---src-pages-contact-tsx-41571656a9dfd5d51b58.js":["Cache-Control: public, max-age=31536000, immutable"],"/component---src-pages-index-tsx-22ac760447d8c24113db.js":["Cache-Control: public, max-age=31536000, immutable"],"/component---src-pages-projects-tsx-ec808ef2eef3b1a0e29c.js":["Cache-Control: public, max-age=31536000, immutable"],"/component---src-pages-skills-tsx-f29f95fb1325764578b4.js":["Cache-Control: public, max-age=31536000, immutable"],"/webpack-runtime-92dc50a7843d12ce6102.js":["Cache-Control: public, max-age=31536000, immutable"],"/framework-aead00b058328e54fb2b.js":["Cache-Control: public, max-age=31536000, immutable"],"/app-782ad1c6008bcb2f8ad7.js":["Cache-Control: public, max-age=31536000, immutable"],"/static/*":["Cache-Control: public, max-age=31536000, immutable"],"/sw.js":["Cache-Control: public, max-age=0, must-revalidate"],"/404/":["Link: </webpack-runtime-92dc50a7843d12ce6102.js>; rel=preload; as=script; nopush","Link: </framework-aead00b058328e54fb2b.js>; rel=preload; as=script; nopush","Link: </app-782ad1c6008bcb2f8ad7.js>; rel=preload; as=script; nopush","Link: </commons-c89ee2ae9b5486d8d1b5.js>; rel=preload; as=script; nopush","Link: </component---src-pages-404-js-fbb7f054aa0b704a0b9a.js>; rel=preload; as=script; nopush","Link: </page-data/app-data.json>; rel=preload; as=fetch; crossorigin; nopush","Link: </page-data/404/page-data.json>; rel=preload; as=fetch; crossorigin; nopush"],"/404.html":["Link: </webpack-runtime-92dc50a7843d12ce6102.js>; rel=preload; as=script; nopush","Link: </framework-aead00b058328e54fb2b.js>; rel=preload; as=script; nopush","Link: </app-782ad1c6008bcb2f8ad7.js>; rel=preload; as=script; nopush","Link: </commons-c89ee2ae9b5486d8d1b5.js>; rel=preload; as=script; nopush","Link: </component---src-pages-404-js-fbb7f054aa0b704a0b9a.js>; rel=preload; as=script; nopush","Link: </page-data/app-data.json>; rel=preload; as=fetch; crossorigin; nopush","Link: </page-data/404.html/page-data.json>; rel=preload; as=fetch; crossorigin; nopush"],"/contact/":["Link: </webpack-runtime-92dc50a7843d12ce6102.js>; rel=preload; as=script; nopush","Link: </framework-aead00b058328e54fb2b.js>; rel=preload; as=script; nopush","Link: </app-782ad1c6008bcb2f8ad7.js>; rel=preload; as=script; nopush","Link: </commons-c89ee2ae9b5486d8d1b5.js>; rel=preload; as=script; nopush","Link: </component---src-pages-contact-tsx-41571656a9dfd5d51b58.js>; rel=preload; as=script; nopush","Link: </page-data/app-data.json>; rel=preload; as=fetch; crossorigin; nopush","Link: </page-data/contact/page-data.json>; rel=preload; as=fetch; crossorigin; nopush"],"/":["Link: </webpack-runtime-92dc50a7843d12ce6102.js>; rel=preload; as=script; nopush","Link: </framework-aead00b058328e54fb2b.js>; rel=preload; as=script; nopush","Link: </app-782ad1c6008bcb2f8ad7.js>; rel=preload; as=script; nopush","Link: </commons-c89ee2ae9b5486d8d1b5.js>; rel=preload; as=script; nopush","Link: </component---src-pages-index-tsx-22ac760447d8c24113db.js>; rel=preload; as=script; nopush","Link: </page-data/app-data.json>; rel=preload; as=fetch; crossorigin; nopush","Link: </page-data/index/page-data.json>; rel=preload; as=fetch; crossorigin; nopush"],"/projects/":["Link: </webpack-runtime-92dc50a7843d12ce6102.js>; rel=preload; as=script; nopush","Link: </framework-aead00b058328e54fb2b.js>; rel=preload; as=script; nopush","Link: </app-782ad1c6008bcb2f8ad7.js>; rel=preload; as=script; nopush","Link: </commons-c89ee2ae9b5486d8d1b5.js>; rel=preload; as=script; nopush","Link: </component---src-pages-projects-tsx-ec808ef2eef3b1a0e29c.js>; rel=preload; as=script; nopush","Link: </page-data/app-data.json>; rel=preload; as=fetch; crossorigin; nopush","Link: </page-data/projects/page-data.json>; rel=preload; as=fetch; crossorigin; nopush"],"/skills/":["Link: </webpack-runtime-92dc50a7843d12ce6102.js>; rel=preload; as=script; nopush","Link: </framework-aead00b058328e54fb2b.js>; rel=preload; as=script; nopush","Link: </app-782ad1c6008bcb2f8ad7.js>; rel=preload; as=script; nopush","Link: </commons-c89ee2ae9b5486d8d1b5.js>; rel=preload; as=script; nopush","Link: </component---src-pages-skills-tsx-f29f95fb1325764578b4.js>; rel=preload; as=script; nopush","Link: </page-data/app-data.json>; rel=preload; as=fetch; crossorigin; nopush","Link: </page-data/skills/page-data.json>; rel=preload; as=fetch; crossorigin; nopush"]}