{"namedChunkGroups":{"polyfill":{"name":"polyfill","assets":[{"name":"webpack-runtime-798fd7dcadd774030291.js","size":5142},{"name":"polyfill-7cfe72322af18fa43511.js","size":82507}],"filteredAssets":0,"assetsSize":87649,"filteredAuxiliaryAssets":2,"auxiliaryAssetsSize":221217},"app":{"name":"app","assets":[{"name":"webpack-runtime-798fd7dcadd774030291.js","size":5142},{"name":"framework-aead00b058328e54fb2b.js","size":128975},{"name":"app-9b3e49ccba7a7c95dde1.js","size":68697}],"filteredAssets":0,"assetsSize":202814,"filteredAuxiliaryAssets":3,"auxiliaryAssetsSize":653457},"component---src-pages-404-js":{"name":"component---src-pages-404-js","assets":[{"name":"styles.0676d15e73c54c2673f4.css","size":9408},{"name":"commons-ab1fef61c1e790371223.js","size":23837},{"name":"component---src-pages-404-js-fbb7f054aa0b704a0b9a.js","size":483}],"filteredAssets":0,"assetsSize":33728,"filteredAuxiliaryAssets":2,"auxiliaryAssetsSize":89399},"component---src-pages-contact-tsx":{"name":"component---src-pages-contact-tsx","assets":[{"name":"styles.0676d15e73c54c2673f4.css","size":9408},{"name":"commons-ab1fef61c1e790371223.js","size":23837},{"name":"component---src-pages-contact-tsx-41571656a9dfd5d51b58.js","size":6099}],"filteredAssets":0,"assetsSize":39344,"filteredAuxiliaryAssets":2,"auxiliaryAssetsSize":99870},"component---src-pages-index-tsx":{"name":"component---src-pages-index-tsx","assets":[{"name":"styles.0676d15e73c54c2673f4.css","size":9408},{"name":"commons-ab1fef61c1e790371223.js","size":23837},{"name":"component---src-pages-index-tsx-4887330d6f1bc1258747.js","size":22535}],"filteredAssets":0,"assetsSize":55780,"filteredAuxiliaryAssets":2,"auxiliaryAssetsSize":176494},"component---src-pages-projects-tsx":{"name":"component---src-pages-projects-tsx","assets":[{"name":"styles.0676d15e73c54c2673f4.css","size":9408},{"name":"commons-ab1fef61c1e790371223.js","size":23837},{"name":"component---src-pages-projects-tsx-a058243a6465bca9272e.js","size":5903}],"filteredAssets":0,"assetsSize":39148,"filteredAuxiliaryAssets":4,"auxiliaryAssetsSize":1096544},"component---src-pages-skills-tsx":{"name":"component---src-pages-skills-tsx","assets":[{"name":"styles.0676d15e73c54c2673f4.css","size":9408},{"name":"commons-ab1fef61c1e790371223.js","size":23837},{"name":"component---src-pages-skills-tsx-9c40bcb7af9b08484cf5.js","size":7271}],"filteredAssets":0,"assetsSize":40516,"filteredAuxiliaryAssets":2,"auxiliaryAssetsSize":106928}},"assetsByChunkName":{"polyfill":["webpack-runtime-798fd7dcadd774030291.js","polyfill-7cfe72322af18fa43511.js"],"app":["webpack-runtime-798fd7dcadd774030291.js","framework-aead00b058328e54fb2b.js","app-9b3e49ccba7a7c95dde1.js"],"component---src-pages-404-js":["styles.0676d15e73c54c2673f4.css","commons-ab1fef61c1e790371223.js","component---src-pages-404-js-fbb7f054aa0b704a0b9a.js"],"component---src-pages-contact-tsx":["styles.0676d15e73c54c2673f4.css","commons-ab1fef61c1e790371223.js","component---src-pages-contact-tsx-41571656a9dfd5d51b58.js"],"component---src-pages-index-tsx":["styles.0676d15e73c54c2673f4.css","commons-ab1fef61c1e790371223.js","component---src-pages-index-tsx-4887330d6f1bc1258747.js"],"component---src-pages-projects-tsx":["styles.0676d15e73c54c2673f4.css","commons-ab1fef61c1e790371223.js","component---src-pages-projects-tsx-a058243a6465bca9272e.js"],"component---src-pages-skills-tsx":["styles.0676d15e73c54c2673f4.css","commons-ab1fef61c1e790371223.js","component---src-pages-skills-tsx-9c40bcb7af9b08484cf5.js"]},"childAssetsByChunkName":{}}